mediaplayer/__init__.py
mediaplayer/admin.py
mediaplayer/app_settings.py
mediaplayer/apps.py
mediaplayer/cms_plugins.py
mediaplayer/forms.py
mediaplayer/models.py
mediaplayer/test_settings.py
mediaplayer/test_urls.py
mediaplayer/views.py
mediaplayer/migrations/__init__.py
mediaplayer/static/mediaplayer/css/mediaplayer.css
mediaplayer/static/mediaplayer/css/mediaplayer.css.map
mediaplayer/static/mediaplayer/css/mediaplayer.scss
mediaplayer/static/mediaplayer/img/backward-solid.svg
mediaplayer/static/mediaplayer/img/expand-solid.svg
mediaplayer/static/mediaplayer/img/forward-solid.svg
mediaplayer/static/mediaplayer/img/icons8-no-audio-24.png
mediaplayer/static/mediaplayer/img/pause-circle-regular.svg
mediaplayer/static/mediaplayer/img/pause-solid.svg
mediaplayer/static/mediaplayer/img/play-circle-regular.svg
mediaplayer/static/mediaplayer/img/play.svg
mediaplayer/static/mediaplayer/img/stop-solid.svg
mediaplayer/static/mediaplayer/img/volume-mute-solid.svg
mediaplayer/static/mediaplayer/img/volume-up-solid.svg
mediaplayer/static/mediaplayer/js/mediaplayer.js
mediaplayer/templates/mediaplayer/audioplayer_plugin.html
mediaplayer/templates/mediaplayer/videoplayer_plugin.html
djangocms_mediaplayer-1.2.16.dist-info/LICENSE
djangocms_mediaplayer-1.2.16.dist-info/METADATA
djangocms_mediaplayer-1.2.16.dist-info/WHEEL
djangocms_mediaplayer-1.2.16.dist-info/top_level.txt
djangocms_mediaplayer-1.2.16.dist-info/RECORD
