Metadata-Version: 2.1
Name: djangocms-mediaplayer
Version: 1.2.16
Summary: A simple and highly customizable audio and video player plugin for the DjangoCMS.
Home-page: https://github.com/domlysi/djangocms_mediaplayer
Author: Dominik Lysiak
Author-email: dominik.lysiak@freenet.de
License: MIT
Platform: UNKNOWN
Classifier: Development Status :: 5 - Production/Stable
Classifier: Environment :: Web Environment
Classifier: Framework :: Django
Classifier: Intended Audience :: Developers
Classifier: License :: OSI Approved :: MIT License
Classifier: Operating System :: OS Independent
Classifier: Programming Language :: Python
Classifier: Programming Language :: Python :: 3
Classifier: Programming Language :: Python :: 3 :: Only
Classifier: Programming Language :: Python :: 3.5
Classifier: Programming Language :: Python :: 3.6
Classifier: Programming Language :: Python :: 3.7
Classifier: Programming Language :: Python :: 3.8
Classifier: Topic :: Internet :: WWW/HTTP
Classifier: Topic :: Software Development :: Libraries :: Python Modules
Requires-Dist: django-filer (>=1.7.0)
Requires-Dist: djangocms-plus
Provides-Extra: test
Requires-Dist: tox (>=2.3) ; extra == 'test'
